Metadata-Version: 2.0
Name: spockbot
Version: 0.1.5
Summary: High level Python framework for building Minecraft clients and bots
Home-page: https://github.com/SpockBotMC/SpockBot
Author: UNKNOWN
Author-email: UNKNOWN
License: MIT
Keywords: minecraft
Platform: UNKNOWN
Classifier: License :: OSI Approved :: MIT License
Requires-Dist: cryptography (>=0.9)
Requires-Dist: minecraft-data (==0.4.0)
Requires-Dist: six
